Metadata-Version: 2.1
Name: libpythonpro-rl
Version: 0.3
Summary: Módulo para exemplificar construção de projetos Python no curso PyTools
Home-page: https://github.com/R-Lemos-prog/libpythonpro
Author: Raiene L. Gonçalves
Author-email: raienelemos@outlook.com
License: GNU AFFERO GENERAL PUBLIC LICENSE
Platform: UNKNOWN
Classifier: Development Status :: 2 - Pre-Alpha
Classifier: Environment :: Console
Classifier: Intended Audience :: Developers
Classifier: License :: OSI Approved :: GNU Affero General Public License v3 or later (AGPLv3+)
Classifier: Operating System :: OS Independent
Classifier: Programming Language :: Python
Classifier: Programming Language :: Python :: 3.9
Classifier: Framework :: Pytest
Classifier: Natural Language :: Portuguese (Brazilian)
